ace/__init__.py
ace/adm_set.py
ace/adm_yang.py
ace/ari.py
ace/ari_cbor.py
ace/cborutil.py
ace/lookup.py
ace/models.py
ace/nickname.py
ace/type_constraint.py
ace/typing.py
ace/util.py
ace/ari_text/__init__.py
ace/ari_text/encode.py
ace/ari_text/lexmod.py
ace/ari_text/parsemod.py
ace/ari_text/util.py
ace/constraints/__init__.py
ace/constraints/basic.py
ace/constraints/core.py
ace/pyang/admtree.py
ace/pyang/dtnma_adm.py
ace/pyang/dtnma_amm.py
ace/tools/__init__.py
ace/tools/ace_adm.py
ace/tools/ace_ari.py
dtnma_ace-2.0.0.dist-info/licenses/LICENSE
dtnma_ace-2.0.0.dist-info/METADATA
dtnma_ace-2.0.0.dist-info/WHEEL
dtnma_ace-2.0.0.dist-info/entry_points.txt
dtnma_ace-2.0.0.dist-info/top_level.txt
dtnma_ace-2.0.0.dist-info/RECORD
