Metadata-Version: 2.4
Name: dtnma-ace
Version: 2.0.0
Summary: DTNMA AMM CODEC Engine (ACE)
Author-email: JHU/APL <dtnma-support@jhuapl.edu>
License-Expression: Apache-2.0
Project-URL: Homepage, https://github.com/JHUAPL-DTNMA/dtnma-ace
Project-URL: Bug Tracker, https://github.com/JHUAPL-DTNMA/dtnma-ace/issues
Classifier: Development Status :: 5 - Production/Stable
Classifier: Programming Language :: Python :: 3
Classifier: Operating System :: OS Independent
Requires-Python: >=3.10
License-File: LICENSE
Requires-Dist: cbor2~=5.6.4
Requires-Dist: cbor-diag
Requires-Dist: numpy
Requires-Dist: PLY>=3
Requires-Dist: portion~=2.4
Requires-Dist: pyang~=2.6
Requires-Dist: setuptools
Requires-Dist: xdg-base-dirs~=6.0
Requires-Dist: sqlalchemy>=1.3
Provides-Extra: test
Requires-Dist: pytest; extra == "test"
Requires-Dist: pytest-subtests; extra == "test"
Requires-Dist: pytest-cov; extra == "test"
Requires-Dist: coverage; extra == "test"
Provides-Extra: pylint
Requires-Dist: pylint; extra == "pylint"
Requires-Dist: pylint_junit; extra == "pylint"
Provides-Extra: flake8
Requires-Dist: flake8; extra == "flake8"
Requires-Dist: flake8_pyproject; extra == "flake8"
Requires-Dist: flake8_formatter_junit_xml; extra == "flake8"
Provides-Extra: docs
Requires-Dist: sphinx<6; extra == "docs"
Requires-Dist: sphinx_rtd_theme; extra == "docs"
Requires-Dist: sphinx-argparse; extra == "docs"
Dynamic: license-file
